{
  "session_id": "c8e2dc40-bb7f-4ff6-af6d-f0cee455f258",
  "generated_at": "2026-01-07T18:39:15.336162",
  "events": [
    {
      "timestamp": "2026-01-07T18:36:56.962076",
      "event_type": "SESSION_START",
      "level": "INFO",
      "data": {
        "session_id": "c8e2dc40-bb7f-4ff6-af6d-f0cee455f258"
      }
    },
    {
      "timestamp": "2026-01-07T18:36:56.962076",
      "event_type": "CHUNKS_CREATED",
      "level": "INFO",
      "data": {
        "cv_id": "cv_7a7c1a48",
        "total_chunks": 6,
        "chunks": [
          {
            "index": 0,
            "section_type": "summary",
            "candidate_name": " Kamran Alizadeh  Law",
            "job_hopping_score": 0.3,
            "avg_tenure_years": 2.5,
            "total_experience_years": 7.0,
            "position_count": 4,
            "employment_gaps_count": 0,
            "content_preview": "===== CANDIDATE PROFILE:  Kamran Alizadeh  Law =====\n\nCURRENT POSITION: document drafting. Organized"
          },
          {
            "index": 1,
            "section_type": "experience",
            "candidate_name": " Kamran Alizadeh  Law",
            "job_hopping_score": 0.3,
            "avg_tenure_years": 2.5,
            "total_experience_years": 7.0,
            "position_count": 4,
            "employment_gaps_count": 0,
            "content_preview": "JOB POSITION 1 of 4 === CURRENT POSITION ===\n\nTITLE: document drafting. Organized professional\nCOMPA"
          },
          {
            "index": 2,
            "section_type": "experience",
            "candidate_name": " Kamran Alizadeh  Law",
            "job_hopping_score": 0.3,
            "avg_tenure_years": 2.5,
            "total_experience_years": 7.0,
            "position_count": 4,
            "employment_gaps_count": 0,
            "content_preview": "JOB POSITION 2 of 4\n\nTITLE: 2015\nCOMPANY: 2016 | UCLA Law Library\nPERIOD: 2015 - 2016\nDURATION: 1 ye"
          },
          {
            "index": 3,
            "section_type": "experience",
            "candidate_name": " Kamran Alizadeh  Law",
            "job_hopping_score": 0.3,
            "avg_tenure_years": 2.5,
            "total_experience_years": 7.0,
            "position_count": 4,
            "employment_gaps_count": 0,
            "content_preview": "JOB POSITION 3 of 4\n\nTITLE: University of California\nCOMPANY: Los Angeles\nPERIOD: 2014 - 2021\nDURATI"
          },
          {
            "index": 4,
            "section_type": "experience",
            "candidate_name": " Kamran Alizadeh  Law",
            "job_hopping_score": 0.3,
            "avg_tenure_years": 2.5,
            "total_experience_years": 7.0,
            "position_count": 4,
            "employment_gaps_count": 0,
            "content_preview": "JOB POSITION 4 of 4\n\nTITLE: Legal Intern\nCOMPANY: adept at case management, legal research, and\nPERI"
          },
          {
            "index": 5,
            "section_type": "full_cv",
            "candidate_name": " Kamran Alizadeh  Law",
            "job_hopping_score": 0.3,
            "avg_tenure_years": 2.5,
            "total_experience_years": 7.0,
            "position_count": 4,
            "employment_gaps_count": 0,
            "content_preview": "COMPLETE CV for  Kamran Alizadeh  Law\n\nCURRENT ROLE: document drafting. Organized professional\nCOMPA"
          }
        ]
      }
    },
    {
      "timestamp": "2026-01-07T18:37:08.003118",
      "event_type": "SESSION_START",
      "level": "INFO",
      "data": {
        "session_id": "c8e2dc40-bb7f-4ff6-af6d-f0cee455f258"
      }
    },
    {
      "timestamp": "2026-01-07T18:37:08.003118",
      "event_type": "CHUNKS_CREATED",
      "level": "INFO",
      "data": {
        "cv_id": "cv_f58b9c46",
        "total_chunks": 7,
        "chunks": [
          {
            "index": 0,
            "section_type": "summary",
            "candidate_name": " Ji-eun Kim  Business",
            "job_hopping_score": 0.5714285714285714,
            "avg_tenure_years": 1.4,
            "total_experience_years": 7.0,
            "position_count": 5,
            "employment_gaps_count": 0,
            "content_preview": "===== CANDIDATE PROFILE:  Ji-eun Kim  Business =====\n\nCURRENT POSITION: business units\nCURRENT COMPA"
          },
          {
            "index": 1,
            "section_type": "experience",
            "candidate_name": " Ji-eun Kim  Business",
            "job_hopping_score": 0.5714285714285714,
            "avg_tenure_years": 1.4,
            "total_experience_years": 7.0,
            "position_count": 5,
            "employment_gaps_count": 0,
            "content_preview": "JOB POSITION 1 of 5\n\nTITLE: 2018\nCOMPANY: 2020 | Lotte Business Services\nPERIOD: 2018 - 2020\nDURATIO"
          },
          {
            "index": 2,
            "section_type": "experience",
            "candidate_name": " Ji-eun Kim  Business",
            "job_hopping_score": 0.5714285714285714,
            "avg_tenure_years": 1.4,
            "total_experience_years": 7.0,
            "position_count": 5,
            "employment_gaps_count": 0,
            "content_preview": "JOB POSITION 2 of 5\n\nTITLE: 9/10\nCOMPANY: Hyundai Consumer Finance\nPERIOD: 2016 - 2018\nDURATION: 2 y"
          },
          {
            "index": 3,
            "section_type": "experience",
            "candidate_name": " Ji-eun Kim  Business",
            "job_hopping_score": 0.5714285714285714,
            "avg_tenure_years": 1.4,
            "total_experience_years": 7.0,
            "position_count": 5,
            "employment_gaps_count": 0,
            "content_preview": "JOB POSITION 3 of 5\n\nTITLE: 2014\nCOMPANY: 2016 | K-Tech Solutions\nPERIOD: 2014 - 2016\nDURATION: 2 ye"
          },
          {
            "index": 4,
            "section_type": "experience",
            "candidate_name": " Ji-eun Kim  Business",
            "job_hopping_score": 0.5714285714285714,
            "avg_tenure_years": 1.4,
            "total_experience_years": 7.0,
            "position_count": 5,
            "employment_gaps_count": 0,
            "content_preview": "JOB POSITION 4 of 5\n\nTITLE: 2013\nCOMPANY: 2014 | StartUp FinTech\nPERIOD: 2013 - 2014\nDURATION: 1 yea"
          },
          {
            "index": 5,
            "section_type": "experience",
            "candidate_name": " Ji-eun Kim  Business",
            "job_hopping_score": 0.5714285714285714,
            "avg_tenure_years": 1.4,
            "total_experience_years": 7.0,
            "position_count": 5,
            "employment_gaps_count": 0,
            "content_preview": "JOB POSITION 5 of 5 === CURRENT POSITION ===\n\nTITLE: business units\nCOMPANY: ensuring clear, diploma"
          },
          {
            "index": 6,
            "section_type": "full_cv",
            "candidate_name": " Ji-eun Kim  Business",
            "job_hopping_score": 0.5714285714285714,
            "avg_tenure_years": 1.4,
            "total_experience_years": 7.0,
            "position_count": 5,
            "employment_gaps_count": 0,
            "content_preview": "COMPLETE CV for  Ji-eun Kim  Business\n\nCURRENT ROLE: business units\nCOMPANY: ensuring clear, diploma"
          }
        ]
      }
    },
    {
      "timestamp": "2026-01-07T18:37:08.821032",
      "event_type": "SESSION_START",
      "level": "INFO",
      "data": {
        "session_id": "c8e2dc40-bb7f-4ff6-af6d-f0cee455f258"
      }
    },
    {
      "timestamp": "2026-01-07T18:37:08.822033",
      "event_type": "CHUNKS_CREATED",
      "level": "INFO",
      "data": {
        "cv_id": "cv_4fad407b",
        "total_chunks": 6,
        "chunks": [
          {
            "index": 0,
            "section_type": "summary",
            "candidate_name": " Sofia Rossi  Restaurant",
            "job_hopping_score": 1.0,
            "avg_tenure_years": 0.5,
            "total_experience_years": 2.0,
            "position_count": 4,
            "employment_gaps_count": 0,
            "content_preview": "===== CANDIDATE PROFILE:  Sofia Rossi  Restaurant =====\n\nCURRENT POSITION: Oversaw nightly cash reco"
          },
          {
            "index": 1,
            "section_type": "experience",
            "candidate_name": " Sofia Rossi  Restaurant",
            "job_hopping_score": 1.0,
            "avg_tenure_years": 0.5,
            "total_experience_years": 2.0,
            "position_count": 4,
            "employment_gaps_count": 0,
            "content_preview": "JOB POSITION 1 of 4\n\nTITLE: 2017\nCOMPANY: 2018 | Bistro Lumière\nPERIOD: 2017 - 2018\nDURATION: 1 year"
          },
          {
            "index": 2,
            "section_type": "experience",
            "candidate_name": " Sofia Rossi  Restaurant",
            "job_hopping_score": 1.0,
            "avg_tenure_years": 0.5,
            "total_experience_years": 2.0,
            "position_count": 4,
            "employment_gaps_count": 0,
            "content_preview": "JOB POSITION 2 of 4\n\nTITLE: 2016\nCOMPANY: 2017 | Local Pizzeria\nPERIOD: 2016 - 2017\nDURATION: 1 year"
          },
          {
            "index": 3,
            "section_type": "experience",
            "candidate_name": " Sofia Rossi  Restaurant",
            "job_hopping_score": 1.0,
            "avg_tenure_years": 0.5,
            "total_experience_years": 2.0,
            "position_count": 4,
            "employment_gaps_count": 0,
            "content_preview": "JOB POSITION 3 of 4 === CURRENT POSITION ===\n\nTITLE: Oversaw nightly cash reconciliation and invento"
          },
          {
            "index": 4,
            "section_type": "experience",
            "candidate_name": " Sofia Rossi  Restaurant",
            "job_hopping_score": 1.0,
            "avg_tenure_years": 0.5,
            "total_experience_years": 2.0,
            "position_count": 4,
            "employment_gaps_count": 0,
            "content_preview": "JOB POSITION 4 of 4\n\nTITLE: High\nCOMPANY: Volume\nPERIOD: Unknown dates\nDURATION: 0 years\n\nJOB DESCRI"
          },
          {
            "index": 5,
            "section_type": "full_cv",
            "candidate_name": " Sofia Rossi  Restaurant",
            "job_hopping_score": 1.0,
            "avg_tenure_years": 0.5,
            "total_experience_years": 2.0,
            "position_count": 4,
            "employment_gaps_count": 0,
            "content_preview": "COMPLETE CV for  Sofia Rossi  Restaurant\n\nCURRENT ROLE: Oversaw nightly cash reconciliation and inve"
          }
        ]
      }
    },
    {
      "timestamp": "2026-01-07T18:37:09.646048",
      "event_type": "SESSION_START",
      "level": "INFO",
      "data": {
        "session_id": "c8e2dc40-bb7f-4ff6-af6d-f0cee455f258"
      }
    },
    {
      "timestamp": "2026-01-07T18:37:09.646048",
      "event_type": "CHUNKS_CREATED",
      "level": "INFO",
      "data": {
        "cv_id": "cv_a8208348",
        "total_chunks": 5,
        "chunks": [
          {
            "index": 0,
            "section_type": "summary",
            "candidate_name": " Sofia Mendoza ",
            "job_hopping_score": 1.0,
            "avg_tenure_years": 0.3333333333333333,
            "total_experience_years": 2.0,
            "position_count": 3,
            "employment_gaps_count": 0,
            "content_preview": "===== CANDIDATE PROFILE:  Sofia Mendoza  =====\n\nCURRENT POSITION: professional design work\nCURRENT C"
          },
          {
            "index": 1,
            "section_type": "experience",
            "candidate_name": " Sofia Mendoza ",
            "job_hopping_score": 1.0,
            "avg_tenure_years": 0.3333333333333333,
            "total_experience_years": 2.0,
            "position_count": 3,
            "employment_gaps_count": 0,
            "content_preview": "JOB POSITION 1 of 3\n\nTITLE: Bachelor of Fine Arts\nCOMPANY: Graphic Design\nPERIOD: 2022 - 2022\nDURATI"
          },
          {
            "index": 2,
            "section_type": "experience",
            "candidate_name": " Sofia Mendoza ",
            "job_hopping_score": 1.0,
            "avg_tenure_years": 0.3333333333333333,
            "total_experience_years": 2.0,
            "position_count": 3,
            "employment_gaps_count": 0,
            "content_preview": "JOB POSITION 2 of 3\n\nTITLE: 2020\nCOMPANY: 2021 | DesignForward Agency\nPERIOD: 2020 - 2021\nDURATION: "
          },
          {
            "index": 3,
            "section_type": "experience",
            "candidate_name": " Sofia Mendoza ",
            "job_hopping_score": 1.0,
            "avg_tenure_years": 0.3333333333333333,
            "total_experience_years": 2.0,
            "position_count": 3,
            "employment_gaps_count": 0,
            "content_preview": "JOB POSITION 3 of 3 === CURRENT POSITION ===\n\nTITLE: professional design work\nCOMPANY: I have scaled"
          },
          {
            "index": 4,
            "section_type": "full_cv",
            "candidate_name": " Sofia Mendoza ",
            "job_hopping_score": 1.0,
            "avg_tenure_years": 0.3333333333333333,
            "total_experience_years": 2.0,
            "position_count": 3,
            "employment_gaps_count": 0,
            "content_preview": "COMPLETE CV for  Sofia Mendoza \n\nCURRENT ROLE: professional design work\nCOMPANY: I have scaled brand"
          }
        ]
      }
    },
    {
      "timestamp": "2026-01-07T18:37:10.418543",
      "event_type": "SESSION_START",
      "level": "INFO",
      "data": {
        "session_id": "c8e2dc40-bb7f-4ff6-af6d-f0cee455f258"
      }
    },
    {
      "timestamp": "2026-01-07T18:37:10.418543",
      "event_type": "CHUNKS_CREATED",
      "level": "INFO",
      "data": {
        "cv_id": "cv_f4b9b797",
        "total_chunks": 5,
        "chunks": [
          {
            "index": 0,
            "section_type": "summary",
            "candidate_name": " Lotte van der Berg  Camera",
            "job_hopping_score": 0.4,
            "avg_tenure_years": 1.6666666666666667,
            "total_experience_years": 5.0,
            "position_count": 3,
            "employment_gaps_count": 0,
            "content_preview": "===== CANDIDATE PROFILE:  Lotte van der Berg  Camera =====\n\nCURRENT POSITION: sports programming.\nCU"
          },
          {
            "index": 1,
            "section_type": "experience",
            "candidate_name": " Lotte van der Berg  Camera",
            "job_hopping_score": 0.4,
            "avg_tenure_years": 1.6666666666666667,
            "total_experience_years": 5.0,
            "position_count": 3,
            "employment_gaps_count": 0,
            "content_preview": "JOB POSITION 1 of 3\n\nTITLE: 2002\nCOMPANY: 2005 | Rotterdam TV Productions\nPERIOD: 2002 - 2005\nDURATI"
          },
          {
            "index": 2,
            "section_type": "experience",
            "candidate_name": " Lotte van der Berg  Camera",
            "job_hopping_score": 0.4,
            "avg_tenure_years": 1.6666666666666667,
            "total_experience_years": 5.0,
            "position_count": 3,
            "employment_gaps_count": 0,
            "content_preview": "JOB POSITION 2 of 3\n\nTITLE: 2000\nCOMPANY: 2002 | Amsterdam Film Studios\nPERIOD: 2000 - 2002\nDURATION"
          },
          {
            "index": 3,
            "section_type": "experience",
            "candidate_name": " Lotte van der Berg  Camera",
            "job_hopping_score": 0.4,
            "avg_tenure_years": 1.6666666666666667,
            "total_experience_years": 5.0,
            "position_count": 3,
            "employment_gaps_count": 0,
            "content_preview": "JOB POSITION 3 of 3 === CURRENT POSITION ===\n\nTITLE: sports programming.\nCOMPANY: storytelling for b"
          },
          {
            "index": 4,
            "section_type": "full_cv",
            "candidate_name": " Lotte van der Berg  Camera",
            "job_hopping_score": 0.4,
            "avg_tenure_years": 1.6666666666666667,
            "total_experience_years": 5.0,
            "position_count": 3,
            "employment_gaps_count": 0,
            "content_preview": "COMPLETE CV for  Lotte van der Berg  Camera\n\nCURRENT ROLE: sports programming.\nCOMPANY: storytelling"
          }
        ]
      }
    },
    {
      "timestamp": "2026-01-07T18:37:11.240801",
      "event_type": "SESSION_START",
      "level": "INFO",
      "data": {
        "session_id": "c8e2dc40-bb7f-4ff6-af6d-f0cee455f258"
      }
    },
    {
      "timestamp": "2026-01-07T18:37:11.240801",
      "event_type": "CHUNKS_CREATED",
      "level": "INFO",
      "data": {
        "cv_id": "cv_6e0ec2af",
        "total_chunks": 3,
        "chunks": [
          {
            "index": 0,
            "section_type": "summary",
            "candidate_name": " Rahul Patel  Junior Digital",
            "job_hopping_score": 0.0,
            "avg_tenure_years": 4.0,
            "total_experience_years": 4.0,
            "position_count": 1,
            "employment_gaps_count": 0,
            "content_preview": "===== CANDIDATE PROFILE:  Rahul Patel  Junior Digital =====\n\nCURRENT POSITION: crafting data‑driven "
          },
          {
            "index": 1,
            "section_type": "experience",
            "candidate_name": " Rahul Patel  Junior Digital",
            "job_hopping_score": 0.0,
            "avg_tenure_years": 4.0,
            "total_experience_years": 4.0,
            "position_count": 1,
            "employment_gaps_count": 0,
            "content_preview": "JOB POSITION 1 of 1 === CURRENT POSITION ===\n\nTITLE: crafting data‑driven campaigns that boost\nCOMPA"
          },
          {
            "index": 2,
            "section_type": "full_cv",
            "candidate_name": " Rahul Patel  Junior Digital",
            "job_hopping_score": 0.0,
            "avg_tenure_years": 4.0,
            "total_experience_years": 4.0,
            "position_count": 1,
            "employment_gaps_count": 0,
            "content_preview": "COMPLETE CV for  Rahul Patel  Junior Digital\n\nCURRENT ROLE: crafting data‑driven campaigns that boos"
          }
        ]
      }
    },
    {
      "timestamp": "2026-01-07T18:37:12.029692",
      "event_type": "SESSION_START",
      "level": "INFO",
      "data": {
        "session_id": "c8e2dc40-bb7f-4ff6-af6d-f0cee455f258"
      }
    },
    {
      "timestamp": "2026-01-07T18:37:12.029692",
      "event_type": "CHUNKS_CREATED",
      "level": "INFO",
      "data": {
        "cv_id": "cv_6b970919",
        "total_chunks": 4,
        "chunks": [
          {
            "index": 0,
            "section_type": "summary",
            "candidate_name": " Diego Mendoza  Protocol",
            "job_hopping_score": 0.0,
            "avg_tenure_years": 0.0,
            "total_experience_years": 0.0,
            "position_count": 1,
            "employment_gaps_count": 0,
            "content_preview": "===== CANDIDATE PROFILE:  Diego Mendoza  Protocol =====\n\nCURRENT POSITION: Detail\nCURRENT COMPANY: o"
          },
          {
            "index": 1,
            "section_type": "experience",
            "candidate_name": " Diego Mendoza  Protocol",
            "job_hopping_score": 0.0,
            "avg_tenure_years": 0.0,
            "total_experience_years": 0.0,
            "position_count": 1,
            "employment_gaps_count": 0,
            "content_preview": "JOB POSITION 1 of 1 === CURRENT POSITION ===\n\nTITLE: Detail\nCOMPANY: oriented and adaptable Protocol"
          },
          {
            "index": 2,
            "section_type": "skills",
            "candidate_name": " Diego Mendoza  Protocol",
            "job_hopping_score": 0.0,
            "avg_tenure_years": 0.0,
            "total_experience_years": 0.0,
            "position_count": 1,
            "employment_gaps_count": 0,
            "content_preview": "SKILLS AND COMPETENCIES for  Diego Mendoza  Protocol:\n\nDesigning, developing, and implementing secur"
          },
          {
            "index": 3,
            "section_type": "full_cv",
            "candidate_name": " Diego Mendoza  Protocol",
            "job_hopping_score": 0.0,
            "avg_tenure_years": 0.0,
            "total_experience_years": 0.0,
            "position_count": 1,
            "employment_gaps_count": 0,
            "content_preview": "COMPLETE CV for  Diego Mendoza  Protocol\n\nCURRENT ROLE: Detail\nCOMPANY: oriented and adaptable Proto"
          }
        ]
      }
    },
    {
      "timestamp": "2026-01-07T18:37:12.882058",
      "event_type": "SESSION_START",
      "level": "INFO",
      "data": {
        "session_id": "c8e2dc40-bb7f-4ff6-af6d-f0cee455f258"
      }
    },
    {
      "timestamp": "2026-01-07T18:37:12.882058",
      "event_type": "CHUNKS_CREATED",
      "level": "INFO",
      "data": {
        "cv_id": "cv_b143ff08",
        "total_chunks": 6,
        "chunks": [
          {
            "index": 0,
            "section_type": "summary",
            "candidate_name": " Lena Schmidt  Pharmacy",
            "job_hopping_score": 0.2,
            "avg_tenure_years": 3.3333333333333335,
            "total_experience_years": 15.0,
            "position_count": 3,
            "employment_gaps_count": 1,
            "content_preview": "===== CANDIDATE PROFILE:  Lena Schmidt  Pharmacy =====\n\nCURRENT POSITION: healthcare operations. Kno"
          },
          {
            "index": 1,
            "section_type": "experience",
            "candidate_name": " Lena Schmidt  Pharmacy",
            "job_hopping_score": 0.2,
            "avg_tenure_years": 3.3333333333333335,
            "total_experience_years": 15.0,
            "position_count": 3,
            "employment_gaps_count": 1,
            "content_preview": "JOB POSITION 1 of 3\n\nTITLE: 2000\nCOMPANY: 2005 | Cologne Community Pharmacy\nPERIOD: 2000 - 2005\nDURA"
          },
          {
            "index": 2,
            "section_type": "experience",
            "candidate_name": " Lena Schmidt  Pharmacy",
            "job_hopping_score": 0.2,
            "avg_tenure_years": 3.3333333333333335,
            "total_experience_years": 15.0,
            "position_count": 3,
            "employment_gaps_count": 1,
            "content_preview": "JOB POSITION 2 of 3\n\nTITLE: 1990\nCOMPANY: 1995 | Düsseldorf Community Pharmacy\nPERIOD: 1990 - 1995\nD"
          },
          {
            "index": 3,
            "section_type": "experience",
            "candidate_name": " Lena Schmidt  Pharmacy",
            "job_hopping_score": 0.2,
            "avg_tenure_years": 3.3333333333333335,
            "total_experience_years": 15.0,
            "position_count": 3,
            "employment_gaps_count": 1,
            "content_preview": "JOB POSITION 3 of 3 === CURRENT POSITION ===\n\nTITLE: healthcare operations. Known for reliable\nCOMPA"
          },
          {
            "index": 4,
            "section_type": "skills",
            "candidate_name": " Lena Schmidt  Pharmacy",
            "job_hopping_score": 0.2,
            "avg_tenure_years": 3.3333333333333335,
            "total_experience_years": 15.0,
            "position_count": 3,
            "employment_gaps_count": 1,
            "content_preview": "SKILLS AND COMPETENCIES for  Lena Schmidt  Pharmacy:\n\n.com/lena Handled complex prescription process"
          },
          {
            "index": 5,
            "section_type": "full_cv",
            "candidate_name": " Lena Schmidt  Pharmacy",
            "job_hopping_score": 0.2,
            "avg_tenure_years": 3.3333333333333335,
            "total_experience_years": 15.0,
            "position_count": 3,
            "employment_gaps_count": 1,
            "content_preview": "COMPLETE CV for  Lena Schmidt  Pharmacy\n\nCURRENT ROLE: healthcare operations. Known for reliable\nCOM"
          }
        ]
      }
    },
    {
      "timestamp": "2026-01-07T18:37:13.616344",
      "event_type": "SESSION_START",
      "level": "INFO",
      "data": {
        "session_id": "c8e2dc40-bb7f-4ff6-af6d-f0cee455f258"
      }
    },
    {
      "timestamp": "2026-01-07T18:37:13.616344",
      "event_type": "CHUNKS_CREATED",
      "level": "INFO",
      "data": {
        "cv_id": "cv_0049c222",
        "total_chunks": 6,
        "chunks": [
          {
            "index": 0,
            "section_type": "summary",
            "candidate_name": " Aisha Adebayo  Junior",
            "job_hopping_score": 0.42857142857142855,
            "avg_tenure_years": 1.75,
            "total_experience_years": 4.0,
            "position_count": 4,
            "employment_gaps_count": 0,
            "content_preview": "===== CANDIDATE PROFILE:  Aisha Adebayo  Junior =====\n\nCURRENT POSITION: E X P E R I E N C E\nCURRENT"
          },
          {
            "index": 1,
            "section_type": "experience",
            "candidate_name": " Aisha Adebayo  Junior",
            "job_hopping_score": 0.42857142857142855,
            "avg_tenure_years": 1.75,
            "total_experience_years": 4.0,
            "position_count": 4,
            "employment_gaps_count": 0,
            "content_preview": "JOB POSITION 1 of 4\n\nTITLE: Lagos\nCOMPANY: Nigeria\nPERIOD: 2026 - ?\nDURATION: 0 years\n\nJOB DESCRIPTI"
          },
          {
            "index": 2,
            "section_type": "experience",
            "candidate_name": " Aisha Adebayo  Junior",
            "job_hopping_score": 0.42857142857142855,
            "avg_tenure_years": 1.75,
            "total_experience_years": 4.0,
            "position_count": 4,
            "employment_gaps_count": 0,
            "content_preview": "JOB POSITION 2 of 4 === CURRENT POSITION ===\n\nTITLE: E X P E R I E N C E\nCOMPANY: Marketing Intern\nP"
          },
          {
            "index": 3,
            "section_type": "experience",
            "candidate_name": " Aisha Adebayo  Junior",
            "job_hopping_score": 0.42857142857142855,
            "avg_tenure_years": 1.75,
            "total_experience_years": 4.0,
            "position_count": 4,
            "employment_gaps_count": 0,
            "content_preview": "JOB POSITION 3 of 4\n\nTITLE: Expected Graduation\nCOMPANY: GPA: 4.8/5.0\nPERIOD: 2023 - ?\nDURATION: 3 y"
          },
          {
            "index": 4,
            "section_type": "experience",
            "candidate_name": " Aisha Adebayo  Junior",
            "job_hopping_score": 0.42857142857142855,
            "avg_tenure_years": 1.75,
            "total_experience_years": 4.0,
            "position_count": 4,
            "employment_gaps_count": 0,
            "content_preview": "JOB POSITION 4 of 4\n\nTITLE: 2022\nCOMPANY: 2023 | Campus Connect\nPERIOD: 2022 - 2023\nDURATION: 1 year"
          },
          {
            "index": 5,
            "section_type": "full_cv",
            "candidate_name": " Aisha Adebayo  Junior",
            "job_hopping_score": 0.42857142857142855,
            "avg_tenure_years": 1.75,
            "total_experience_years": 4.0,
            "position_count": 4,
            "employment_gaps_count": 0,
            "content_preview": "COMPLETE CV for  Aisha Adebayo  Junior\n\nCURRENT ROLE: E X P E R I E N C E\nCOMPANY: Marketing Intern\n"
          }
        ]
      }
    },
    {
      "timestamp": "2026-01-07T18:37:14.417979",
      "event_type": "SESSION_START",
      "level": "INFO",
      "data": {
        "session_id": "c8e2dc40-bb7f-4ff6-af6d-f0cee455f258"
      }
    },
    {
      "timestamp": "2026-01-07T18:37:14.418980",
      "event_type": "CHUNKS_CREATED",
      "level": "INFO",
      "data": {
        "cv_id": "cv_3dbd895b",
        "total_chunks": 3,
        "chunks": [
          {
            "index": 0,
            "section_type": "summary",
            "candidate_name": " Aisha Chen  Junior Smart Contract",
            "job_hopping_score": 0.0,
            "avg_tenure_years": 1.0,
            "total_experience_years": 1.0,
            "position_count": 1,
            "employment_gaps_count": 0,
            "content_preview": "===== CANDIDATE PROFILE:  Aisha Chen  Junior Smart Contract =====\n\nCURRENT POSITION: \nCURRENT COMPA"
          },
          {
            "index": 1,
            "section_type": "experience",
            "candidate_name": " Aisha Chen  Junior Smart Contract",
            "job_hopping_score": 0.0,
            "avg_tenure_years": 1.0,
            "total_experience_years": 1.0,
            "position_count": 1,
            "employment_gaps_count": 0,
            "content_preview": "JOB POSITION 1 of 1 === CURRENT POSITION ===\n\nTITLE: \nCOMPANY: Lagos, Nigeria\nPERIOD: 2023 - Presen"
          },
          {
            "index": 2,
            "section_type": "full_cv",
            "candidate_name": " Aisha Chen  Junior Smart Contract",
            "job_hopping_score": 0.0,
            "avg_tenure_years": 1.0,
            "total_experience_years": 1.0,
            "position_count": 1,
            "employment_gaps_count": 0,
            "content_preview": "COMPLETE CV for  Aisha Chen  Junior Smart Contract\n\nCURRENT ROLE: \nCOMPANY: Lagos, Nigeria\nTOTAL EX"
          }
        ]
      }
    },
    {
      "timestamp": "2026-01-07T18:37:15.188525",
      "event_type": "SESSION_START",
      "level": "INFO",
      "data": {
        "session_id": "c8e2dc40-bb7f-4ff6-af6d-f0cee455f258"
      }
    },
    {
      "timestamp": "2026-01-07T18:37:15.188525",
      "event_type": "CHUNKS_CREATED",
      "level": "INFO",
      "data": {
        "cv_id": "cv_0bcfa366",
        "total_chunks": 4,
        "chunks": [
          {
            "index": 0,
            "section_type": "summary",
            "candidate_name": " Kwame Addo  Celebrity",
            "job_hopping_score": 0.125,
            "avg_tenure_years": 4.0,
            "total_experience_years": 4.0,
            "position_count": 2,
            "employment_gaps_count": 0,
            "content_preview": "===== CANDIDATE PROFILE:  Kwame Addo  Celebrity =====\n\nCURRENT POSITION: styling and fashion trend a"
          },
          {
            "index": 1,
            "section_type": "experience",
            "candidate_name": " Kwame Addo  Celebrity",
            "job_hopping_score": 0.125,
            "avg_tenure_years": 4.0,
            "total_experience_years": 4.0,
            "position_count": 2,
            "employment_gaps_count": 0,
            "content_preview": "JOB POSITION 1 of 2 === CURRENT POSITION ===\n\nTITLE: styling and fashion trend analysis.\nCOMPANY: S "
          },
          {
            "index": 2,
            "section_type": "experience",
            "candidate_name": " Kwame Addo  Celebrity",
            "job_hopping_score": 0.125,
            "avg_tenure_years": 4.0,
            "total_experience_years": 4.0,
            "position_count": 2,
            "employment_gaps_count": 0,
            "content_preview": "JOB POSITION 2 of 2\n\nTITLE: First Class Honours\nCOMPANY: Dean's List\nPERIOD: 2022 - ?\nDURATION: 4 ye"
          },
          {
            "index": 3,
            "section_type": "full_cv",
            "candidate_name": " Kwame Addo  Celebrity",
            "job_hopping_score": 0.125,
            "avg_tenure_years": 4.0,
            "total_experience_years": 4.0,
            "position_count": 2,
            "employment_gaps_count": 0,
            "content_preview": "COMPLETE CV for  Kwame Addo  Celebrity\n\nCURRENT ROLE: styling and fashion trend analysis.\nCOMPANY: S"
          }
        ]
      }
    },
    {
      "timestamp": "2026-01-07T18:37:15.945541",
      "event_type": "SESSION_START",
      "level": "INFO",
      "data": {
        "session_id": "c8e2dc40-bb7f-4ff6-af6d-f0cee455f258"
      }
    },
    {
      "timestamp": "2026-01-07T18:37:15.946539",
      "event_type": "CHUNKS_CREATED",
      "level": "INFO",
      "data": {
        "cv_id": "cv_842b07d5",
        "total_chunks": 6,
        "chunks": [
          {
            "index": 0,
            "section_type": "summary",
            "candidate_name": " Aisha Al Mansoori ",
            "job_hopping_score": 0.3333333333333333,
            "avg_tenure_years": 2.25,
            "total_experience_years": 6.0,
            "position_count": 4,
            "employment_gaps_count": 0,
            "content_preview": "===== CANDIDATE PROFILE:  Aisha Al Mansoori  =====\n\nCURRENT POSITION: E X P E R I E N C E\nCURRENT CO"
          },
          {
            "index": 1,
            "section_type": "experience",
            "candidate_name": " Aisha Al Mansoori ",
            "job_hopping_score": 0.3333333333333333,
            "avg_tenure_years": 2.25,
            "total_experience_years": 6.0,
            "position_count": 4,
            "employment_gaps_count": 0,
            "content_preview": "JOB POSITION 1 of 4 === CURRENT POSITION ===\n\nTITLE: E X P E R I E N C E\nCOMPANY: Postdoctoral Resea"
          },
          {
            "index": 2,
            "section_type": "experience",
            "candidate_name": " Aisha Al Mansoori ",
            "job_hopping_score": 0.3333333333333333,
            "avg_tenure_years": 2.25,
            "total_experience_years": 6.0,
            "position_count": 4,
            "employment_gaps_count": 0,
            "content_preview": "JOB POSITION 2 of 4\n\nTITLE: Abu Dhabi\nCOMPANY: UAE Machine Learning (ICML 2023).\nPERIOD: 2023 - ?\nDU"
          },
          {
            "index": 3,
            "section_type": "experience",
            "candidate_name": " Aisha Al Mansoori ",
            "job_hopping_score": 0.3333333333333333,
            "avg_tenure_years": 2.25,
            "total_experience_years": 6.0,
            "position_count": 4,
            "employment_gaps_count": 0,
            "content_preview": "JOB POSITION 3 of 4 === CURRENT POSITION ===\n\nTITLE: 2022\nCOMPANY: 2024 | Institute of Advanced Stud"
          },
          {
            "index": 4,
            "section_type": "experience",
            "candidate_name": " Aisha Al Mansoori ",
            "job_hopping_score": 0.3333333333333333,
            "avg_tenure_years": 2.25,
            "total_experience_years": 6.0,
            "position_count": 4,
            "employment_gaps_count": 0,
            "content_preview": "JOB POSITION 4 of 4\n\nTITLE: 2020\nCOMPANY: 2022 | National University of UAE\nPERIOD: 2020 - 2022\nDURA"
          },
          {
            "index": 5,
            "section_type": "full_cv",
            "candidate_name": " Aisha Al Mansoori ",
            "job_hopping_score": 0.3333333333333333,
            "avg_tenure_years": 2.25,
            "total_experience_years": 6.0,
            "position_count": 4,
            "employment_gaps_count": 0,
            "content_preview": "COMPLETE CV for  Aisha Al Mansoori \n\nCURRENT ROLE: E X P E R I E N C E\nCOMPANY: Postdoctoral Researc"
          }
        ]
      }
    },
    {
      "timestamp": "2026-01-07T18:37:16.808379",
      "event_type": "SESSION_START",
      "level": "INFO",
      "data": {
        "session_id": "c8e2dc40-bb7f-4ff6-af6d-f0cee455f258"
      }
    },
    {
      "timestamp": "2026-01-07T18:37:16.808379",
      "event_type": "CHUNKS_CREATED",
      "level": "INFO",
      "data": {
        "cv_id": "cv_d97bac5e",
        "total_chunks": 4,
        "chunks": [
          {
            "index": 0,
            "section_type": "summary",
            "candidate_name": " Lukas Schneider ",
            "job_hopping_score": 1.0,
            "avg_tenure_years": 0.5,
            "total_experience_years": 1.0,
            "position_count": 2,
            "employment_gaps_count": 0,
            "content_preview": "===== CANDIDATE PROFILE:  Lukas Schneider  =====\n\nCURRENT POSITION: and outfit assembly.\nCURRENT COM"
          },
          {
            "index": 1,
            "section_type": "experience",
            "candidate_name": " Lukas Schneider ",
            "job_hopping_score": 1.0,
            "avg_tenure_years": 0.5,
            "total_experience_years": 1.0,
            "position_count": 2,
            "employment_gaps_count": 0,
            "content_preview": "JOB POSITION 1 of 2\n\nTITLE: 2012\nCOMPANY: 2013 | Fashion Forward GmbH\nPERIOD: 2012 - 2013\nDURATION: "
          },
          {
            "index": 2,
            "section_type": "experience",
            "candidate_name": " Lukas Schneider ",
            "job_hopping_score": 1.0,
            "avg_tenure_years": 0.5,
            "total_experience_years": 1.0,
            "position_count": 2,
            "employment_gaps_count": 0,
            "content_preview": "JOB POSITION 2 of 2 === CURRENT POSITION ===\n\nTITLE: and outfit assembly.\nCOMPANY: brand identities "
          },
          {
            "index": 3,
            "section_type": "full_cv",
            "candidate_name": " Lukas Schneider ",
            "job_hopping_score": 1.0,
            "avg_tenure_years": 0.5,
            "total_experience_years": 1.0,
            "position_count": 2,
            "employment_gaps_count": 0,
            "content_preview": "COMPLETE CV for  Lukas Schneider \n\nCURRENT ROLE: and outfit assembly.\nCOMPANY: brand identities acro"
          }
        ]
      }
    },
    {
      "timestamp": "2026-01-07T18:37:17.646817",
      "event_type": "SESSION_START",
      "level": "INFO",
      "data": {
        "session_id": "c8e2dc40-bb7f-4ff6-af6d-f0cee455f258"
      }
    },
    {
      "timestamp": "2026-01-07T18:37:17.646817",
      "event_type": "CHUNKS_CREATED",
      "level": "INFO",
      "data": {
        "cv_id": "cv_e513854f",
        "total_chunks": 3,
        "chunks": [
          {
            "index": 0,
            "section_type": "summary",
            "candidate_name": " Lucien Moreau  Creature",
            "job_hopping_score": 0.0,
            "avg_tenure_years": 26.0,
            "total_experience_years": 26.0,
            "position_count": 1,
            "employment_gaps_count": 0,
            "content_preview": "===== CANDIDATE PROFILE:  Lucien Moreau  Creature =====\n\nCURRENT POSITION: English ⭐⭐⭐⭐⭐⭐\nCURRENT CO"
          },
          {
            "index": 1,
            "section_type": "experience",
            "candidate_name": " Lucien Moreau  Creature",
            "job_hopping_score": 0.0,
            "avg_tenure_years": 26.0,
            "total_experience_years": 26.0,
            "position_count": 1,
            "employment_gaps_count": 0,
            "content_preview": "JOB POSITION 1 of 1 === CURRENT POSITION ===\n\nTITLE: English ⭐⭐⭐⭐⭐⭐\nCOMPANY: (Professional) groundwo"
          },
          {
            "index": 2,
            "section_type": "full_cv",
            "candidate_name": " Lucien Moreau  Creature",
            "job_hopping_score": 0.0,
            "avg_tenure_years": 26.0,
            "total_experience_years": 26.0,
            "position_count": 1,
            "employment_gaps_count": 0,
            "content_preview": "COMPLETE CV for  Lucien Moreau  Creature\n\nCURRENT ROLE: English ⭐⭐⭐⭐⭐⭐\nCOMPANY: (Professional) groun"
          }
        ]
      }
    },
    {
      "timestamp": "2026-01-07T18:37:27.685299",
      "event_type": "SESSION_START",
      "level": "INFO",
      "data": {
        "session_id": "c8e2dc40-bb7f-4ff6-af6d-f0cee455f258"
      }
    },
    {
      "timestamp": "2026-01-07T18:37:27.685299",
      "event_type": "QUERY_START",
      "level": "INFO",
      "data": {
        "question": "Give me the top 3 candidates for the position",
        "cv_ids": [
          "cv_f333b1a3",
          "cv_4cd8f7f7",
          "cv_d761f72b",
          "cv_4379cb94",
          "cv_ea1ff2c0",
          "cv_c5bd5b5d",
          "cv_7bcd5fe9",
          "cv_d1e7f0b9",
          "cv_1ce92745",
          "cv_1e3e62ab",
          "cv_add18e3c",
          "cv_c81e909b",
          "cv_7a311638",
          "cv_ee559421",
          "cv_7a7c1a48",
          "cv_f58b9c46",
          "cv_4fad407b",
          "cv_a8208348",
          "cv_f4b9b797",
          "cv_6e0ec2af",
          "cv_6b970919",
          "cv_b143ff08",
          "cv_0049c222",
          "cv_3dbd895b",
          "cv_0bcfa366",
          "cv_842b07d5",
          "cv_d97bac5e",
          "cv_e513854f"
        ],
        "cv_count": 28
      }
    },
    {
      "timestamp": "2026-01-07T18:37:41.001303",
      "event_type": "RETRIEVAL",
      "level": "INFO",
      "data": {
        "total_chunks": 10,
        "strategy": "rrf_fusion",
        "sample_chunks": [
          {
            "index": 0,
            "cv_id": "cv_4cd8f7f7",
            "candidate_name": " Aisha Adebayo  Game",
            "section_type": "experience",
            "job_hopping_score": 0.05263157894736842,
            "avg_tenure_years": 12.666666666666666,
            "total_experience_years": 32.0,
            "score": 0.6546361081255111,
            "has_enriched_metadata": true
          },
          {
            "index": 1,
            "cv_id": "cv_b143ff08",
            "candidate_name": " Lena Schmidt  Pharmacy",
            "section_type": "experience",
            "job_hopping_score": 0.2,
            "avg_tenure_years": 3.3333333333333335,
            "total_experience_years": 15.0,
            "score": 0.6110243937105798,
            "has_enriched_metadata": true
          },
          {
            "index": 2,
            "cv_id": "cv_1ce92745",
            "candidate_name": " Chukwudi Okeke  iOS",
            "section_type": "experience",
            "job_hopping_score": 0.4,
            "avg_tenure_years": 1.6666666666666667,
            "total_experience_years": 3.0,
            "score": 0.5971301155864459,
            "has_enriched_metadata": true
          },
          {
            "index": 3,
            "cv_id": "cv_f333b1a3",
            "candidate_name": " Giulia Rossi  Junior Mobile",
            "section_type": "experience",
            "job_hopping_score": 0.25,
            "avg_tenure_years": 2.0,
            "total_experience_years": 3.0,
            "score": 0.5963599625619006,
            "has_enriched_metadata": true
          },
          {
            "index": 4,
            "cv_id": "cv_7a311638",
            "candidate_name": " Sofia Rodriguez  Junior",
            "section_type": "experience",
            "job_hopping_score": 0.3333333333333333,
            "avg_tenure_years": 2.0,
            "total_experience_years": 6.0,
            "score": 0.5960732469355556,
            "has_enriched_metadata": true
          },
          {
            "index": 5,
            "cv_id": "cv_ea1ff2c0",
            "candidate_name": " Sofia Hernandez  Frontend",
            "section_type": "experience",
            "job_hopping_score": 0.14285714285714285,
            "avg_tenure_years": 4.666666666666667,
            "total_experience_years": 14.0,
            "score": 0.5956251239302752,
            "has_enriched_metadata": true
          },
          {
            "index": 6,
            "cv_id": "cv_7bcd5fe9",
            "candidate_name": " Sofia Bianchi  Associate Mobile",
            "section_type": "experience",
            "job_hopping_score": 0.6666666666666666,
            "avg_tenure_years": 1.0,
            "total_experience_years": 3.0,
            "score": 0.5917937725199873,
            "has_enriched_metadata": true
          },
          {
            "index": 7,
            "cv_id": "cv_f4b9b797",
            "candidate_name": " Lotte van der Berg  Camera",
            "section_type": "experience",
            "job_hopping_score": 0.4,
            "avg_tenure_years": 1.6666666666666667,
            "total_experience_years": 5.0,
            "score": 0.59042308027546,
            "has_enriched_metadata": true
          },
          {
            "index": 8,
            "cv_id": "cv_f58b9c46",
            "candidate_name": " Ji-eun Kim  Business",
            "section_type": "full_cv",
            "job_hopping_score": 0.5714285714285714,
            "avg_tenure_years": 1.4,
            "total_experience_years": 7.0,
            "score": 0.5856292422427808,
            "has_enriched_metadata": true
          },
          {
            "index": 9,
            "cv_id": "cv_add18e3c",
            "candidate_name": " Matteo Rossi  Junior Mobile",
            "section_type": "experience",
            "job_hopping_score": 1.0,
            "avg_tenure_years": 0.6666666666666666,
            "total_experience_years": 4.0,
            "score": 0.5847000049931638,
            "has_enriched_metadata": true
          }
        ],
        "all_metadata_keys": [
          "section_type",
          "candidate_name",
          "job_title",
          "company",
          "start_year",
          "end_year",
          "is_current",
          "duration_years",
          "position_order",
          "total_experience_years",
          "job_hopping_score",
          "avg_tenure_years",
          "employment_gaps_count",
          "position_count",
          "skills",
          "seniority_level",
          "certifications",
          "location",
          "filename",
          "cv_id"
        ]
      }
    },
    {
      "timestamp": "2026-01-07T18:37:55.235802",
      "event_type": "TEMPLATE_SELECTION",
      "level": "INFO",
      "data": {
        "template": "QUERY_TEMPLATE",
        "candidate_name": null,
        "detection_method": "explicit_multi_candidate_query"
      }
    },
    {
      "timestamp": "2026-01-07T18:38:20.606240",
      "event_type": "STRUCTURE_ROUTING",
      "level": "INFO",
      "data": {
        "query_type": "ranking",
        "candidate_name": null,
        "detection_source": "classify_query_for_structure",
        "detection_method": "explicit_multi_candidate_query"
      }
    },
    {
      "timestamp": "2026-01-07T18:38:20.734865",
      "event_type": "FINAL_RESPONSE",
      "level": "INFO",
      "data": {
        "answer_length": 1907,
        "answer_preview": ":::thinking\n- The user is asking for the top 3 candidates.\n- I need to analyze the provided CVs and identify the best 3 candidates based on the available information.\n- I will use the provided CV data to determine the candidates' skills and experience.\n- I will use the candidate's job titles and skills to determine their suitability for a technical role.\n- I will rank the candidates based on the relevance of their skills and experience.\n- I will provide the top 3 candidates in the requested form...",
        "has_structured_output": true,
        "structured_output_keys": [
          "direct_answer",
          "raw_content",
          "thinking",
          "analysis",
          "table_data",
          "conclusion",
          "gap_analysis",
          "red_flags",
          "timeline",
          "risk_assessment",
          "structure_type",
          "single_candidate_data",
          "risk_assessment_data",
          "results_table",
          "total_results",
          "query",
          "ranking_table",
          "top_pick",
          "ranking_criteria",
          "match_scores",
          "requirements",
          "best_match",
          "team_composition",
          "skill_coverage",
          "team_risks",
          "team_requirements",
          "claim",
          "evidence",
          "verdict",
          "talent_pool",
          "skill_distribution",
          "experience_distribution",
          "cv_references",
          "parsing_warnings",
          "fallback_used"
        ]
      }
    },
    {
      "timestamp": "2026-01-07T18:38:24.522646",
      "event_type": "SESSION_START",
      "level": "INFO",
      "data": {
        "session_id": "c8e2dc40-bb7f-4ff6-af6d-f0cee455f258"
      }
    },
    {
      "timestamp": "2026-01-07T18:38:24.523151",
      "event_type": "QUERY_START",
      "level": "INFO",
      "data": {
        "question": "How many candidates have senior experience?",
        "cv_ids": [
          "cv_f333b1a3",
          "cv_4cd8f7f7",
          "cv_d761f72b",
          "cv_4379cb94",
          "cv_ea1ff2c0",
          "cv_c5bd5b5d",
          "cv_7bcd5fe9",
          "cv_d1e7f0b9",
          "cv_1ce92745",
          "cv_1e3e62ab",
          "cv_add18e3c",
          "cv_c81e909b",
          "cv_7a311638",
          "cv_ee559421",
          "cv_7a7c1a48",
          "cv_f58b9c46",
          "cv_4fad407b",
          "cv_a8208348",
          "cv_f4b9b797",
          "cv_6e0ec2af",
          "cv_6b970919",
          "cv_b143ff08",
          "cv_0049c222",
          "cv_3dbd895b",
          "cv_0bcfa366",
          "cv_842b07d5",
          "cv_d97bac5e",
          "cv_e513854f"
        ],
        "cv_count": 28
      }
    },
    {
      "timestamp": "2026-01-07T18:38:39.665628",
      "event_type": "RETRIEVAL",
      "level": "INFO",
      "data": {
        "total_chunks": 10,
        "strategy": "rrf_fusion",
        "sample_chunks": [
          {
            "index": 0,
            "cv_id": "cv_842b07d5",
            "candidate_name": " Aisha Al Mansoori ",
            "section_type": "experience",
            "job_hopping_score": 0.3333333333333333,
            "avg_tenure_years": 2.25,
            "total_experience_years": 6.0,
            "score": 0.550366220584702,
            "has_enriched_metadata": true
          },
          {
            "index": 1,
            "cv_id": "cv_c81e909b",
            "candidate_name": " Liam OConnor  Junior",
            "section_type": "experience",
            "job_hopping_score": 0.4,
            "avg_tenure_years": 1.6666666666666667,
            "total_experience_years": 5.0,
            "score": 0.5436207921673366,
            "has_enriched_metadata": true
          },
          {
            "index": 2,
            "cv_id": "cv_a8208348",
            "candidate_name": " Sofia Mendoza ",
            "section_type": "experience",
            "job_hopping_score": 1.0,
            "avg_tenure_years": 0.3333333333333333,
            "total_experience_years": 2.0,
            "score": 0.538802500359086,
            "has_enriched_metadata": true
          },
          {
            "index": 3,
            "cv_id": "cv_add18e3c",
            "candidate_name": " Matteo Rossi  Junior Mobile",
            "section_type": "experience",
            "job_hopping_score": 1.0,
            "avg_tenure_years": 0.6666666666666666,
            "total_experience_years": 4.0,
            "score": 0.5378685904032632,
            "has_enriched_metadata": true
          },
          {
            "index": 4,
            "cv_id": "cv_7bcd5fe9",
            "candidate_name": " Sofia Bianchi  Associate Mobile",
            "section_type": "experience",
            "job_hopping_score": 0.6666666666666666,
            "avg_tenure_years": 1.0,
            "total_experience_years": 3.0,
            "score": 0.526300125373347,
            "has_enriched_metadata": true
          },
          {
            "index": 5,
            "cv_id": "cv_7a311638",
            "candidate_name": " Sofia Rodriguez  Junior",
            "section_type": "experience",
            "job_hopping_score": 0.3333333333333333,
            "avg_tenure_years": 2.0,
            "total_experience_years": 6.0,
            "score": 0.5243184035946249,
            "has_enriched_metadata": true
          },
          {
            "index": 6,
            "cv_id": "cv_1e3e62ab",
            "candidate_name": " Annelies de Vries  Junior Web",
            "section_type": "full_cv",
            "job_hopping_score": 1.0,
            "avg_tenure_years": 0.5,
            "total_experience_years": 1.0,
            "score": 0.5230328663172222,
            "has_enriched_metadata": true
          },
          {
            "index": 7,
            "cv_id": "cv_f58b9c46",
            "candidate_name": " Ji-eun Kim  Business",
            "section_type": "experience",
            "job_hopping_score": 0.5714285714285714,
            "avg_tenure_years": 1.4,
            "total_experience_years": 7.0,
            "score": 0.5210016523973645,
            "has_enriched_metadata": true
          },
          {
            "index": 8,
            "cv_id": "cv_f333b1a3",
            "candidate_name": " Giulia Rossi  Junior Mobile",
            "section_type": "experience",
            "job_hopping_score": 0.25,
            "avg_tenure_years": 2.0,
            "total_experience_years": 3.0,
            "score": 0.5189717727645428,
            "has_enriched_metadata": true
          },
          {
            "index": 9,
            "cv_id": "cv_0049c222",
            "candidate_name": " Aisha Adebayo  Junior",
            "section_type": "experience",
            "job_hopping_score": 0.42857142857142855,
            "avg_tenure_years": 1.75,
            "total_experience_years": 4.0,
            "score": 0.5170498174681121,
            "has_enriched_metadata": true
          }
        ],
        "all_metadata_keys": [
          "section_type",
          "candidate_name",
          "job_title",
          "company",
          "start_year",
          "end_year",
          "is_current",
          "duration_years",
          "position_order",
          "total_experience_years",
          "job_hopping_score",
          "avg_tenure_years",
          "employment_gaps_count",
          "position_count",
          "skills",
          "seniority_level",
          "certifications",
          "location",
          "filename",
          "cv_id"
        ]
      }
    },
    {
      "timestamp": "2026-01-07T18:38:50.425331",
      "event_type": "TEMPLATE_SELECTION",
      "level": "INFO",
      "data": {
        "template": "QUERY_TEMPLATE",
        "candidate_name": null,
        "detection_method": "multiple_candidates"
      }
    },
    {
      "timestamp": "2026-01-07T18:39:15.211276",
      "event_type": "STRUCTURE_ROUTING",
      "level": "INFO",
      "data": {
        "query_type": "summary",
        "candidate_name": null,
        "detection_source": "classify_query_for_structure",
        "detection_method": "multiple_candidates"
      }
    },
    {
      "timestamp": "2026-01-07T18:39:15.334185",
      "event_type": "FINAL_RESPONSE",
      "level": "INFO",
      "data": {
        "answer_length": 621,
        "answer_preview": ":::thinking\n- The user is asking how many candidates have senior experience.\n- I need to analyze the provided CVs and identify candidates with \"senior\" in their job titles or descriptions.\n- I will then provide the number of candidates and list them.\n- I will use the exact candidate names and cv_ids.\n- I will not make any assumptions.\n- I will not include any skills that are not explicitly mentioned in the CV.\n- I will adhere to the output format.\n:::\n\n\n:::conclusion\n2 candidates partially match...",
        "has_structured_output": true,
        "structured_output_keys": [
          "direct_answer",
          "raw_content",
          "thinking",
          "analysis",
          "table_data",
          "conclusion",
          "gap_analysis",
          "red_flags",
          "timeline",
          "risk_assessment",
          "structure_type",
          "single_candidate_data",
          "risk_assessment_data",
          "results_table",
          "total_results",
          "query",
          "ranking_table",
          "top_pick",
          "ranking_criteria",
          "match_scores",
          "requirements",
          "best_match",
          "team_composition",
          "skill_coverage",
          "team_risks",
          "team_requirements",
          "claim",
          "evidence",
          "verdict",
          "talent_pool",
          "skill_distribution",
          "experience_distribution",
          "cv_references",
          "parsing_warnings",
          "fallback_used"
        ]
      }
    }
  ]
}